{
  "display": {
    "icon": {
      "item": "anal_craft:ancientseemeningot"
    },
    "title": {
      "translate": "advancements.slitok.title"
    },
    "description": {
      "translate": "advancements.slitok.descr"
    },
    "frame": "task",
    "show_toast": true,
    "announce_to_chat": true,
    "hidden": false
  },
  "criteria": {
    "slitok": {
      "trigger": "minecraft:inventory_changed",
      "conditions": {
        "items": [
          {
            "item": "anal_craft:ancientseemeningot",
            "count": {
              "min": 1,
              "max": 1
            }
          }
        ]
      }
    }
  },
  "rewards": {
    "experience": 1
  },
  "parent": "anal_craft:forestadva"
}