{
  "group": "anal_craft",
  "type": "minecraft:crafting_shaped",
  "pattern": [
    "01",
    "23",
    "45"
  ],
  "key": {
    "0": {
      "item": "minecraft:flint"
    },
    "1": {
      "item": "minecraft:flint"
    },
    "2": {
      "item": "anal_craft:cumplanks"
    },
    "3": {
      "item": "anal_craft:cumplanks"
    },
    "4": {
      "item": "anal_craft:cumplanks"
    },
    "5": {
      "item": "anal_craft:cumplanks"
    }
  },
  "result": {
    "item": "minecraft:fletching_table",
    "count": 1
  }
}